pokerprobs/__init__.py
pokerprobs/get_nuts.py
pokerprobs/hand_odds.py
pokerprobs/play_game.py
pokerprobs-0.0.1.dist-info/LICENSE
pokerprobs-0.0.1.dist-info/METADATA
pokerprobs-0.0.1.dist-info/WHEEL
pokerprobs-0.0.1.dist-info/top_level.txt
pokerprobs-0.0.1.dist-info/RECORD
