Metadata-Version: 2.1
Name: pokerprobs
Version: 0.0.1
Summary: poker_hand_probabilities
Home-page: UNKNOWN
Author: Elijah Cavan
Author-email: eli_cavan@live.ca
License: UNKNOWN
Keywords: python,first package
Platform: UNKNOWN
Classifier: Development Status :: 3 - Alpha
Classifier: Intended Audience :: Education
Classifier: Programming Language :: Python :: 2
Classifier: Programming Language :: Python :: 3
Classifier: Operating System :: MacOS :: MacOS X
Classifier: Operating System :: Microsoft :: Windows
